Workbook

Sheet Index New
A1: Lexeme | B1: Flexeme | C1: Definition Code | D1: M-W Code | E1: Definition | F1: Notes
A2: 1. Eat | B2: ate ppt | D2: Intransitive
C3: 1(1a) | D3: 1a | E3: To take food or a meal.
C4: 1(2a) | D4: 2a | E4: To affect something by gradual destruction or comsumption. Usually used with 'into', 'away', or 'at'. "The loss was really eating at her." "The controvery ate into his support."
D6: Transitive
C7: 1(3a) | D7: 3a | E7: To take in through the mouth as food. To ingest, chew, and swallow in turn.
C8: 1(4a) | D8: 4a | E8: To destroy, consume, or waste by or as if by eating. "Expenses ate up the profits." "gadgets that eat up too much space"
C9: 1(4b) | D9: 4b | E9: To bear the expense of. To take a loss on. "The team was forced to eat the rest of his contract."
C10: 1(5a) | D10: 5a | E10: To consume gradually. To corrode. "cars eaten away by rust"
C11: 1(5b) | D11: 5b | E11: To consume with vexation. To bother. "What's eating you now?"
C12: 1(6a) | D12: 6a | E12: To enjoy eagerly or avidly. To lap. Usually used with 'up'. "It was an amazing performace and the crowd ate it up.
C13: 1(7a) | D13: 7a | E13: (Usually vulgar) To perform fellatio or cunnilingus on. Often used with 'out'.
C14: 1(8a) | D14: 8a | E14: Phrases: eat it (to fall or be injured) | F14: I added this one.
A16: 2. Begin | B16: began ppt | D16: Intransitive
C17: 2(1a) | D17: 1a | E17: To do the first part of an action. To go into the first part of a process. To start. "Began by introducing herself" "will have to begin again"
C18: 2(2a) | D18: 2a | E18: To come into existence. To arise. "Their problems were just beginning."
C19: 2(2b) | D19: 2b | E19: To have a starting point. "Her career began in Chicago." "Prices begin at $110 per night."
C20: 2(3a) | D20: 3a | E20: To do or succeed in the least degree. "I can't begin to tell you how pleased I am." | F20: This feels transitive to me.
D22: Transitive
C23: 2(4a) | D23: 4a | E23: To set about the activity of. To start. "They began the lecture at 10:00." "have already begun construction"
C24: 2(5a) | D24: 5a | E24: To bring into being. To found. "credited with beginning the movement" "In 1819, he married the daughter of … chief and began a dynasty that would last for nearly 200 years."
C25: 2(5b) | D25: 5b | E25: To originate. To invent. "began their tradition"
A27: 3. Bid | B27: bid pst | D27: Intransitive
B28: bidden ppt | C28: 3(1a) | D28: 1a | E28: To make a bid. "Several other companies bid on the job."
C29: 3(2a) | D29: 2a | E29: Phrase: to bid fair. To seem likely. "a movie that bids fair to become a big hit"
D31: Transitive
C32: 3(3a) | D32: 3a | E32: To offer (a price) whether for payment or acceptance. "The contractor bid $10,000 less than his nearest competitor."
C33: 3(3b) | D33: 3b | E33: Card games: To make a bid of or in (a suit of cards). "bid one spade"
C34: 3(3c) | D34: 3c | E34: To offer. Usually used in the phrase 'to bid defiance'. "The poorest man may in his cottage bid defiance to all the forces of the Crown."
C35: 3(4a) | D35: 4a | E35: To issue an order to. To tell. "did as I was bid" | F35: Overlap between 4a and 4c
C36: 3(4b) | D36: 4b | E36: To request to come. To invite. "were bidden to the wedding"
C37: 3(4c) | D37: 4c | E37: To beseech or entreat. (obsolete)
C38: 3(5a) | D38: 5a | E38: To give expression to. "bade a tearful farewell"
C39: 3(6a) | D39: 6a | E39: Phrase: to bid on | F39: Not in Merriam-Webster
A41: 4. Break | B41: broke ppt | D41: Intransitive
C42: 4(1a) | D42: 1a | E42: To escape with sudden forceful effort. "The attacker broke from the throng."
C43: 4(1b) | D43: 1b | E43: To come into being by or as if by bursting forth. "day was breaking"
C44: 4(1f) | D44: 1f | E44: To become known or published. "when the news broke"
C45: 4(1g) | D45: 1g | E45: To make a sudden dash. "break for cover"
C46: 4(2a) | D46: 2a | E46: To come apart or split into pieces. To fragment. To shatter. "The cup broke when it fell"
C47: 4(2b) | D47: 2b | E47: To open spontaneously or by pressure from within. "The blister broke."
C48: 4(7a) | D48: 7a | E48: To end a relationship, connection, or agreement; usually used with with or from. "break with tradition" "broke with the leadership"
C49: 4(10a) | D49: 10a | E49: To fail in health, strength, vitality, resolve, or control. "may break under questioning"
C50: 4(10b) | D50: 10b | E50: To become inoperative because of damage, wear, or strain. "The pump broke."
C51: 4(13a) | D51: 13a | E51: To happen. To develop. "For the team to succeed, everything has to break right."
C52: 4(16a) | D52: 16a | E52: Phrases: break a leg, break bread, break camp, break cover, break covert, break even, break free, break ground, break into, break one's heart, break one's wrists, break ranks, break rank, break the back of, break the ice, break wind
D54: Transitive
C55: 4(17a) | D55: 17a | E55: To separate into parts with suddenness or violence. "broke the plate" "Break the chocolate bar in half."
C56: 4(17b) | D56: 17b | E56: To cause (a bone) to separate into two or more pieces. To fracture. "broke her femur" To fracture a bone of (a bodily part). "The blow broke her arm." To dislocate or dislocate and fracture a bone of (the neck or back)
C57: 4(18a) | D57: 18a | E57: To violate. To transgress. "break the law" "break a promise" "breaking conventions"
C58: 4(19a) | D58: 19a | E58: (Archaic) To force entry into.
C59: 4(19c) | D59: 19c | E59: To escape by force from. "break jail"
C60: 4(21a) | D60: 21a | E60: To make ineffective as a binding force. "break the spell"
C61: 4(22b) | D61: 22b | E61: To crush the spirit of. "brutal methods broke the prisoner"
C62: 4(23a) | D62: 23a | E62: To stop or bring to an end suddenly. To halt. "break a deadlock" "breaking a bad habit" "decided to break off all ties to the organization"
C63: 4(23f) | D63: 23f | E63: To split the surface of. "could see fish breaking the water"
C64: 4(24a) | D64: 24a | E64: To make known. To tell. "break the news gently"
C65: 4(25a) | D65: 25a | E65: To ruin financialy. "break the bank"
C66: 4(26a) | D66: 26a | E66: To split into smaller units, parts, or processes. To divide. "break the grammar lesson into digestible chunks." "break a word at the end of a line"
... C71: 4(33b) | D71: 33b | E71: To produce visibility. "barely breaks a sweat"
A73: 5. Bring | B73: brung pst | D73: Intransitive
C74: 5(1a) | D74: 1a | E74: (Chiefly Midland US) To yield. To produce.
C75: 5(2a) | D75: 2a | E75: Phrases: bring up the rear
D77: Transitive
C78: 5(3a) | D78: 3a | E78: To convey, lead, carry, or cause to come along with one toward the place from which the action is being regarded. "brought a bottle of wine to the party"
C79: 5(3b) | D79: 3b | E79: To cause to be, act, or move in a special way: such as: To attract. "Her screams brought the neighbors."
C80: 5(3c) | D80: 3c | E80: To persuade. To induce. "try to bring them to his way of thinking" To force. To compel. "was brought before a judge"
C81: 5(3d) | D81: 3d | E81: To cause to come into a particular state or condition. "bring water to a boil"
C82: 5(3e) | D82: 3e | E82: (Dialect) To escort. To accompany. "May I bring you home?"
C83: 5(3f) | D83: 3f | E83: To bear as an attribute or characteristic. "brings years of experience to the position"
C84: 5(4a) | D84: 4a | E84: To cause to exist or occur. Such as: To be the occasion of. "Winter brings snow." To result in. "The drug brought immediate relief." "brought tears to her eyes" To institute. "bring legal action" To adduce. "bring an argument"
C85: 5(5a) | D85: 5a | E85: To prefer. "whether to bring legal charges against him"
C86: 5(6a) | D86: 6a | E86: To procure in exchange. To sell for. "should bring a high price at auction"
C87: 5(7a) | D87: 7a | E87: Phrases: bring forth, bring forward, bring home, bring to account, bring to bear, bring to book, bring to light, bring to mind, bring to terms
A89: 6. Burn | B89: burnt ppt | D89: Intransitive
B90: burnt pst | C90: 6(1a) | D90: 1a | E90: To consume fuel and give off heat, light, and gases. "A small fire burns on the hearth."
C91: 6(1b) | D91: 1b | E91: To undergo combustion. Also, to undergo nuclear fission or nuclear fusion.
C92: 6(1c) | D92: 1c | E92: To contain a fire. "a little stove burning in the corner"
C93: 6(1d) | D93: 1d | E93: To give off light. To shine or glow. "a light burning in the window"
C94: 6(2a) | D94: 2a | E94: To be hot. "the burning sand"
C95: 6(2b) | D95: 2b | E95: To produce or undergo discomfort or pain. "ears burning from the cold"
C96: 6(2c) | D96: 2c | E96: To become emotionally excited or agitated. "burning to tell the story" "the remark made him burn"
C97: 6(3a) | D97: 3a | E97: To undergo alteration or destruction by the action of fire or heat. "The house burned down." "The potatoes burned to a crisp."
C98: 6(3b) | D98: 3b | E98: To die in the electric chair.
C99: 6(3c) | D99: 3c | E99: To diminish in intensity. Possibly, to be extinguished altogether. | F99: Not in Merriam-Webster
C100: 6(4a) | D100: 4a | E100: To force or make a way as if by burning. "Her words burned into his heart."
C101: 6(5a) | D101: 5a | E101: To suffer sunburn. "She burns easily."
C102: 6(6a) | D102: 6a | E102: To suffer burnount.
D104: Transitive
C105: 6(7a) | D105: 7a | E105: To cause to undergo combustion. Especially, to destroy by fire. "burned the trash" | F105: Overlap between 7a and 9a
C106: 6(7b) | D106: 7b | E106: To use as fuel. "This furnace burns gas"
C107: 6(7c) | D107: 7c | E107: To use up. To consume. "burn calories"
C108: 6(8a) | D108: 8a | E108: To transform by exposure to heat or fire. "burn clay to bricks"
C109: 6(8b) | D109: 8b | E109: To produce by burning. "burned a hole in his sleeve"
C110: 6(8c) | D110: 8c | E110: To record digital data or music on (an optical disk) using a laser. Also, to record (data or music) in this way. "burn a CD" "burn songs onto a disk"
C111: 6(9a) | D111: 9a | E111: To injure or damage by or as if by exposure to fire, heat, or radiation. To scorch. "burned his hand"
C112: 6(9b) | D112: 9b | E112: To execute by burning. Also, to electrocute. "burned heretics at the stake"
C113: 6(10a) | D113: 10a | E113: To irritate or annoy. Often used with "up". "really burns me up"
C114: 6(10b) | D114: 10b | E114: To subject to misfortune, mistreatment, or deception. Often used in passive. "has been burned in love"
C115: 6(10c) | D115: 10c | E115: To beat a score on. "burned the defense with a touchdown pass"
...

Sheet Main Data
A1: meaning_index | B1: transitive | C1: intrans_corr_meaning_index | D1: metaphor | E1: iffy | F1: meaning | G1: meaning_notes | H1: lexeme | I1: mps | J1: form | K1: ID | L1: source | M1: text
A2: 1(3a) | B2: 1 | C2: 1 | D2: ? | F2: =_xlfn.XLOOKUP($A:$A,'Index New'!C:C,'Index New'!E:E,"") -> To take in through the mouth as food. To ingest, chew, and swallow in turn. | G2: =_xlfn.LET( _xlpm.r, _xlfn.XLOOKUP(A2,'Index New'!C:C,'Index New'!F:F,""), IF(_xlpm.r=0,"",_xlpm.r) ) | H2: eat | I2: ppt | J2: ate | K2: 3 | L2: Chicago Med | M2: 5186683 What? What? Well, I've ate the biscuits, Did you come to prepare for lessons Dewey. And I took
A3: 1(1a) | F3: =_xlfn.XLOOKUP($A:$A,'Index New'!C:C,'Index New'!E:E,"") -> To take food or a meal. | G3: =_xlfn.LET( _xlpm.r, _xlfn.XLOOKUP(A3,'Index New'!C:C,'Index New'!F:F,""), IF(_xlpm.r=0,"",_xlpm.r) ) | H3: eat | I3: ppt | J3: ate | K3: 4 | L3: Mercy Street | M3: bit. Orderly? Nurse? Yes, soldier? Two days. Haven't ate in two days. Please. Just bring some food. You ain't wearing
A4: 1(7a) | B4: 1 | D4: 1 | F4: =_xlfn.XLOOKUP($A:$A,'Index New'!C:C,'Index New'!E:E,"") -> (Usually vulgar) To perform fellatio or cunnilingus on. Often used with 'out'. | G4: =_xlfn.LET( _xlpm.r, _xlfn.XLOOKUP(A4,'Index New'!C:C,'Index New'!F:F,""), IF(_xlpm.r=0,"",_xlpm.r) ) | H4: eat | I4: ppt | J4: ate | K4: 5 | L4: Survivor's Remorse | M4: , he'll be through. See, my Jupiter like to get his ass ate after brain. And they get the dingleberries and everything. What's a dingleberry
A5: 1(3a) | B5: 1 | C5: 1 | F5: =_xlfn.XLOOKUP($A:$A,'Index New'!C:C,'Index New'!E:E,"") -> To take in through the mouth as food. To ingest, chew, and swallow in turn. | G5: =_xlfn.LET( _xlpm.r, _xlfn.XLOOKUP(A5,'Index New'!C:C,'Index New'!F:F,""), IF(_xlpm.r=0,"",_xlpm.r) ) | H5: eat | I5: ppt | J5: ate | K5: 7 | L5: Clarence | M5: . " Clarence: Did you know they got free cookies? I must have ate, like, two bags' worth. And then this old lady thought that
A6: 1(3a) | B6: 1 | C6: 1 | F6: =_xlfn.XLOOKUP($A:$A,'Index New'!C:C,'Index New'!E:E,"") -> To take in through the mouth as food. To ingest, chew, and swallow in turn. | G6: =_xlfn.LET( _xlpm.r, _xlfn.XLOOKUP(A6,'Index New'!C:C,'Index New'!F:F,""), IF(_xlpm.r=0,"",_xlpm.r) ) | H6: eat | I6: ppt | J6: ate | K6: 8 | L6: Teenage Mutant Ninja... | M6: - [groans] Ugh. Oh, I feel awful. Maybe I shouldn't have ate That jalapeno cappuccino pizza last night. [groans] Huh? [screams] What the - -
A7: 1(1a) | F7: =_xlfn.XLOOKUP($A:$A,'Index New'!C:C,'Index New'!E:E,"") -> To take food or a meal. | G7: =_xlfn.LET( _xlpm.r, _xlfn.XLOOKUP(A7,'Index New'!C:C,'Index New'!F:F,""), IF(_xlpm.r=0,"",_xlpm.r) ) | H7: eat | I7: ppt | J7: ate | K7: 9 | L7: Hell's Kitchen | M7: and home these last three days. And you talking about that you ain't ate? Let's see if there's anything to eat. I'm trying to
A8: 1(3a) | B8: 1 | C8: 1 | F8: =_xlfn.XLOOKUP($A:$A,'Index New'!C:C,'Index New'!E:E,"") -> To take in through the mouth as food. To ingest, chew, and swallow in turn. | G8: =_xlfn.LET( _xlpm.r, _xlfn.XLOOKUP(A8,'Index New'!C:C,'Index New'!F:F,""), IF(_xlpm.r=0,"",_xlpm.r) ) | H8: eat | I8: ppt | J8: ate | K8: 11 | L8: foodnetworkhumor.com | M8: have feelings? They're also living beings. Is it murder when they are ate in a salad? Oh, it's different then no? # Everyone needs
A9: 1(3a) | B9: 1 | C9: 1 | F9: =_xlfn.XLOOKUP($A:$A,'Index New'!C:C,'Index New'!E:E,"") -> To take in through the mouth as food. To ingest, chew, and swallow in turn. | G9: =_xlfn.LET( _xlpm.r, _xlfn.XLOOKUP(A9,'Index New'!C:C,'Index New'!F:F,""), IF(_xlpm.r=0,"",_xlpm.r) ) | H9: eat | I9: ppt | J9: ate | K9: 15 | L9: yelp.com | M9: Zoo deal ($17 for RT lift and buffet breakfast) and wished I had ate breakfast elsewhere. I know what you're thinking it's just breakfast; how
A10: 1(3a) | B10: 1 | C10: 1 | F10: =_xlfn.XLOOKUP($A:$A,'Index New'!C:C,'Index New'!E:E,"") -> To take in through the mouth as food. To ingest, chew, and swallow in turn. | G10: =_xlfn.LET( _xlpm.r, _xlfn.XLOOKUP(A10,'Index New'!C:C,'Index New'!F:F,""), IF(_xlpm.r=0,"",_xlpm.r) ) | H10: eat | I10: ppt | J10: ate | K10: 16 | L10: ...al.library.upenn.edu | M10: face and smelt it, and then said, " This kris good -- has ate a man. " # I could not sleep much, there were such strange
A11: 1(3a) | B11: 1 | C11: 1 | F11: =_xlfn.XLOOKUP($A:$A,'Index New'!C:C,'Index New'!E:E,"") -> To take in through the mouth as food. To ingest, chew, and swallow in turn. | G11: =_xlfn.LET( _xlpm.r, _xlfn.XLOOKUP(A11,'Index New'!C:C,'Index New'!F:F,""), IF(_xlpm.r=0,"",_xlpm.r) ) | H11: eat | I11: ppt | J11: ate | K11: 20 | L11: bible.cc | M11: a religious one; moderation in all ought to be used; and whatever is ate or drank, should be received with thankfulness, and done to the glory of
A12: 1(3a) | B12: 1 | C12: 1 | F12: =_xlfn.XLOOKUP($A:$A,'Index New'!C:C,'Index New'!E:E,"") -> To take in through the mouth as food. To ingest, chew, and swallow in turn. | G12: =_xlfn.LET( _xlpm.r, _xlfn.XLOOKUP(A12,'Index New'!C:C,'Index New'!F:F,""), IF(_xlpm.r=0,"",_xlpm.r) ) | H12: eat | I12: ppt | J12: ate | K12: 25 | L12: kingarthurflour.com | M12: . Elisabeth # We are so doing this! I love the idea and have ate food art that my kids have created that haven't been as cute or appetizing
A13: 1(1a) | F13: =_xlfn.XLOOKUP($A:$A,'Index New'!C:C,'Index New'!E:E,"") -> To take food or a meal. | G13: =_xlfn.LET( _xlpm.r, _xlfn.XLOOKUP(A13,'Index New'!C:C,'Index New'!F:F,""), IF(_xlpm.r=0,"",_xlpm.r) ) | H13: eat | I13: ppt | J13: ate | K13: 31 | L13: answers.yahoo.com | M13: seem to be hungry about an half hour later and feel like I haven't ate all day. My stomach gets a really weird airy feeling like its empty and
A14: 1(3a) | C14: 1 | F14: =_xlfn.XLOOKUP($A:$A,'Index New'!C:C,'Index New'!E:E,"") -> To take in through the mouth as food. To ingest, chew, and swallow in turn. | G14: =_xlfn.LET( _xlpm.r, _xlfn.XLOOKUP(A14,'Index New'!C:C,'Index New'!F:F,""), IF(_xlpm.r=0,"",_xlpm.r) ) | H14: eat | I14: ppt | J14: ate | K14: 36 | L14: eatocracy.cnn.com | M14: us). Whether the woman was pregnant of not, she should not have ate the sandwich while shopping. That would include a parent opening up a package of
A15: 1(3a) | B15: 1 | C15: 1 | F15: =_xlfn.XLOOKUP($A:$A,'Index New'!C:C,'Index New'!E:E,"") -> To take in through the mouth as food. To ingest, chew, and swallow in turn. | G15: =_xlfn.LET( _xlpm.r, _xlfn.XLOOKUP(A15,'Index New'!C:C,'Index New'!F:F,""), IF(_xlpm.r=0,"",_xlpm.r) ) | H15: eat | I15: ppt | J15: ate | K15: 37 | L15: fanfiction.net | M15: room checking the huge computer. # " Aw come on I haven't even ate one pancake! " Beast Boy complained following everyone into the living room. Robin
A16: 1(5b) | B16: 1 | D16: 1 | F16: =_xlfn.XLOOKUP($A:$A,'Index New'!C:C,'Index New'!E:E,"") -> To consume with vexation. To bother. "What's eating you now?" | G16: =_xlfn.LET( _xlpm.r, _xlfn.XLOOKUP(A16,'Index New'!C:C,'Index New'!F:F,""), IF(_xlpm.r=0,"",_xlpm.r) ) | H16: eat | I16: ppt | J16: ate | K16: 38 | L16: tvtropes.org | M16: Bomb of the Year, as Punk called out Laurinaitis for how it must've ate him alive with jealousy that while his brother was one of the legendary Road Warriors
A17: 1(1a) | F17: =_xlfn.XLOOKUP($A:$A,'Index New'!C:C,'Index New'!E:E,"") -> To take food or a meal. | G17: =_xlfn.LET( _xlpm.r, _xlfn.XLOOKUP(A17,'Index New'!C:C,'Index New'!F:F,""), IF(_xlpm.r=0,"",_xlpm.r) ) | H17: eat | I17: ppt | J17: ate | K17: 40 | L17: bible.cc | M17: as do the Jews; that is, he had done so, he had ate with the Gentiles, and as the Gentiles did, without regarding the laws and
A18: 1(7a) | B18: 1 | D18: 1 | F18: =_xlfn.XLOOKUP($A:$A,'Index New'!C:C,'Index New'!E:E,"") -> (Usually vulgar) To perform fellatio or cunnilingus on. Often used with 'out'. | G18: =_xlfn.LET( _xlpm.r, _xlfn.XLOOKUP(A18,'Index New'!C:C,'Index New'!F:F,""), IF(_xlpm.r=0,"",_xlpm.r) ) | H18: eat | I18: ppt | J18: ate | K18: 41 | L18: elyrics.net | M18: Shawty body shaped like a figure eight Yeah that pussy great She bout to get ate # Verse 1: It was a Friday I was on the highway Riding to
A19: 1(3a) | B19: 1 | C19: 1 | F19: =_xlfn.XLOOKUP($A:$A,'Index New'!C:C,'Index New'!E:E,"") -> To take in through the mouth as food. To ingest, chew, and swallow in turn. | G19: =_xlfn.LET( _xlpm.r, _xlfn.XLOOKUP(A19,'Index New'!C:C,'Index New'!F:F,""), IF(_xlpm.r=0,"",_xlpm.r) ) | H19: eat | I19: ppt | J19: ate | K19: 42 | L19: sparkpeople.com | M19: feel SO guilty for going over, BUT, I wonder if I would have ate some protein in the morning, if I would have felt the need to eat
A20: 1(3a) | B20: 1 | C20: 1 | F20: =_xlfn.XLOOKUP($A:$A,'Index New'!C:C,'Index New'!E:E,"") -> To take in through the mouth as food. To ingest, chew, and swallow in turn. | G20: =_xlfn.LET( _xlpm.r, _xlfn.XLOOKUP(A20,'Index New'!C:C,'Index New'!F:F,""), IF(_xlpm.r=0,"",_xlpm.r) ) | H20: eat | I20: ppt | J20: ate | K20: 45 | L20: bible.cc | M20: ; his stomach is empty when he awakes, and he finds he has not ate anything at all: # or as when a thirsty man dreameth, and,
A21: 1(8a) | B21: 1 | D21: 1 | F21: =_xlfn.XLOOKUP($A:$A,'Index New'!C:C,'Index New'!E:E,"") -> Phrases: eat it (to fall or be injured) | G21: =_xlfn.LET( _xlpm.r, _xlfn.XLOOKUP(A21,'Index New'!C:C,'Index New'!F:F,""), IF(_xlpm.r=0,"",_xlpm.r) ) -> I added this one. | H21: eat | I21: ppt | J21: ate | K21: 46 | L21: yelp.com | M21: a fall. I'm scared of stairs though. I'm sure someone has ate it here before, though. And I'm terrified that person will one day
A22: 1(3a) | B22: 1 | C22: 1 | F22: =_xlfn.XLOOKUP($A:$A,'Index New'!C:C,'Index New'!E:E,"") -> To take in through the mouth as food. To ingest, chew, and swallow in turn. | G22: =_xlfn.LET( _xlpm.r, _xlfn.XLOOKUP(A22,'Index New'!C:C,'Index New'!F:F,""), IF(_xlpm.r=0,"",_xlpm.r) ) | H22: eat | I22: ppt | J22: ate | K22: 47 | L22: pitt.edu | M22: . " # Best or worst, " says the girl, " I've ate' em all, and you can't have one till that's come again
A23: 1(3a) | B23: 1 | C23: 1 | D23: ? | F23: =_xlfn.XLOOKUP($A:$A,'Index New'!C:C,'Index New'!E:E,"") -> To take in through the mouth as food. To ingest, chew, and swallow in turn. | G23: =_xlfn.LET( _xlpm.r, _xlfn.XLOOKUP(A23,'Index New'!C:C,'Index New'!F:F,""), IF(_xlpm.r=0,"",_xlpm.r) ) | H23: eat | I23: ppt | J23: ate | K23: 49 | L23: scienceline.org | M23: about it # I am a+ and my body temp. is 96.8 I get ate by a lot of bugs all the time. If I scratch at them,
A24: 1(1a) | F24: =_xlfn.XLOOKUP($A:$A,'Index New'!C:C,'Index New'!E:E,"") -> To take food or a meal. | G24: =_xlfn.LET( _xlpm.r, _xlfn.XLOOKUP(A24,'Index New'!C:C,'Index New'!F:F,""), IF(_xlpm.r=0,"",_xlpm.r) ) | H24: eat | I24: ppt | J24: ate | K24: 50 | L24: huffingtonpost.com | M24: see each other all the time. Plus by 7 o clock everybody should have ate and went home. The only holiday my family celebrate pass 9 is forth of
A25: 1(3a) | B25: 1 | C25: 1 | F25: =_xlfn.XLOOKUP($A:$A,'Index New'!C:C,'Index New'!E:E,"") -> To take in through the mouth as food. To ingest, chew, and swallow in turn. | G25: =_xlfn.LET( _xlpm.r, _xlfn.XLOOKUP(A25,'Index New'!C:C,'Index New'!F:F,""), IF(_xlpm.r=0,"",_xlpm.r) ) | H25: eat | I25: ppt | J25: ate | K25: 52 | L25: literature.org | M25: surveying one small atom of a bone upon the dish), they hadn't ate it all at last! Yet every one had had enough, and the youngest
A26: 1(5a) | B26: 1 | D26: 1 | E26: 1 | F26: =_xlfn.XLOOKUP($A:$A,'Index New'!C:C,'Index New'!E:E,"") -> To consume gradually. To corrode. "cars eaten away by rust" | G26: =_xlfn.LET( _xlpm.r, _xlfn.XLOOKUP(A26,'Index New'!C:C,'Index New'!F:F,""), IF(_xlpm.r=0,"",_xlpm.r) ) | H26: eat | I26: ppt | J26: ate | K26: 53 | L26: etsy.com | M26: priority international. I charge a flat rate that covers the cost. I have ate some $ on a few international orders but just by some change so that's
A27: 1(3a) | B27: 1 | C27: 1 | F27: =_xlfn.XLOOKUP($A:$A,'Index New'!C:C,'Index New'!E:E,"") -> To take in through the mouth as food. To ingest, chew, and swallow in turn. | G27: =_xlfn.LET( _xlpm.r, _xlfn.XLOOKUP(A27,'Index New'!C:C,'Index New'!F:F,""), IF(_xlpm.r=0,"",_xlpm.r) ) | H27: eat | I27: ppt | J27: ate | K27: 54 | L27: ...or.blogs.nytimes.com | M27: Matter of Fashion Tags: # " Much was said, and much was ate, and all went well. " Clearly this sentence was written by a fourth
A28: 1(3a) | B28: 1 | C28: 1 | F28: =_xlfn.XLOOKUP($A:$A,'Index New'!C:C,'Index New'!E:E,"") -> To take in through the mouth as food. To ingest, chew, and swallow in turn. | G28: =_xlfn.LET( _xlpm.r, _xlfn.XLOOKUP(A28,'Index New'!C:C,'Index New'!F:F,""), IF(_xlpm.r=0,"",_xlpm.r) ) | H28: eat | I28: ppt | J28: ate | K28: 55 | L28: ed.msnbc.com | M28: this have to with being president. When Romney was in France he may have ate horse as they do so what? # OO Should be weened off mothers milk
A29: 1(1a) | F29: =_xlfn.XLOOKUP($A:$A,'Index New'!C:C,'Index New'!E:E,"") -> To take food or a meal. | G29: =_xlfn.LET( _xlpm.r, _xlfn.XLOOKUP(A29,'Index New'!C:C,'Index New'!F:F,""), IF(_xlpm.r=0,"",_xlpm.r) ) | H29: eat | I29: ppt | J29: ate | K29: 58 | L29: ...documentaryfilms.com | M29: we act as if it was? # don't judge someone until they've ate good. don't even judge then, you don't know if they are
A30: 1(3a) | B30: 1 | C30: 1 | F30: =_xlfn.XLOOKUP($A:$A,'Index New'!C:C,'Index New'!E:E,"") -> To take in through the mouth as food. To ingest, chew, and swallow in turn. | G30: =_xlfn.LET( _xlpm.r, _xlfn.XLOOKUP(A30,'Index New'!C:C,'Index New'!F:F,""), IF(_xlpm.r=0,"",_xlpm.r) ) | H30: eat | I30: ppt | J30: ate | K30: 60 | L30: asianfanfics.com | M30: # pshinyeong-som on says: Shinyeong happily swallowed the ice cream. She hasn't ate it for years now. She loved the taste of the ice cream. "
A31: 1(3a) | B31: 1 | C31: 1 | F31: =_xlfn.XLOOKUP($A:$A,'Index New'!C:C,'Index New'!E:E,"") -> To take in through the mouth as food. To ingest, chew, and swallow in turn. | G31: =_xlfn.LET( _xlpm.r, _xlfn.XLOOKUP(A31,'Index New'!C:C,'Index New'!F:F,""), IF(_xlpm.r=0,"",_xlpm.r) ) | H31: eat | I31: ppt | J31: ate | K31: 61 | L31: mediaite.com | M31: tried to revive his idea of immigration reform, the gNOpigs turned on him and ate him alive. Newt Gingrich had a similar view a bit more recently, and
A32: 1(3a) | B32: 1 | C32: 1 | F32: =_xlfn.XLOOKUP($A:$A,'Index New'!C:C,'Index New'!E:E,"") -> To take in through the mouth as food. To ingest, chew, and swallow in turn. | G32: =_xlfn.LET( _xlpm.r, _xlfn.XLOOKUP(A32,'Index New'!C:C,'Index New'!F:F,""), IF(_xlpm.r=0,"",_xlpm.r) ) | H32: eat | I32: ppt | J32: ate | K32: 63 | L32: ...stcity.posterous.com | M32: Even lived their whole lives wondering what could have been if only they had not ate of the forbidden fruit. Judas Iscariot is living the rest of his eternity in
A33: 1(1a) | F33: =_xlfn.XLOOKUP($A:$A,'Index New'!C:C,'Index New'!E:E,"") -> To take food or a meal. | G33: =_xlfn.LET( _xlpm.r, _xlfn.XLOOKUP(A33,'Index New'!C:C,'Index New'!F:F,""), IF(_xlpm.r=0,"",_xlpm.r) ) | H33: eat | I33: ppt | J33: ate | K33: 65 | L33: ...lthouse.blogspot.com | M33: one came and I got in. Nice cab. Everything spotless. Could have ate off the floor. Black driver. Fer'ner. Accent. Looked muslim, I
A34: 1(3a) | B34: 1 | C34: 1 | F34: =_xlfn.XLOOKUP($A:$A,'Index New'!C:C,'Index New'!E:E,"") -> To take in through the mouth as food. To ingest, chew, and swallow in turn. | G34: =_xlfn.LET( _xlpm.r, _xlfn.XLOOKUP(A34,'Index New'!C:C,'Index New'!F:F,""), IF(_xlpm.r=0,"",_xlpm.r) ) | H34: eat | I34: ppt | J34: ate | K34: 67 | L34: theafwife.com | M34: it was extremely condensed coffee... we are talking I may as well have just ate the grounds. # Like I said, MONDAY morning. I need my freaking
A35: 1(5a) | B35: 1 | D35: 1 | E35: 1 | F35: =_xlfn.XLOOKUP($A:$A,'Index New'!C:C,'Index New'!E:E,"") -> To consume gradually. To corrode. "cars eaten away by rust" | G35: =_xlfn.LET( _xlpm.r, _xlfn.XLOOKUP(A35,'Index New'!C:C,'Index New'!F:F,""), IF(_xlpm.r=0,"",_xlpm.r) ) | H35: eat | I35: ppt | J35: ate | K35: 70 | L35: nakedcapitalism.com | M35: , in an effort to survive when faced with no bailouts etc, would have ate their own and settled these issues amongst themselves. Instead we are left with the
A36: 1(3a) | B36: 1 | C36: 1 | F36: =_xlfn.XLOOKUP($A:$A,'Index New'!C:C,'Index New'!E:E,"") -> To take in through the mouth as food. To ingest, chew, and swallow in turn. | G36: =_xlfn.LET( _xlpm.r, _xlfn.XLOOKUP(A36,'Index New'!C:C,'Index New'!F:F,""), IF(_xlpm.r=0,"",_xlpm.r) ) | H36: eat | I36: ppt | J36: ate | K36: 75 | L36: tortoiseforum.org | M36: 5 days ago and he got shipped to me. Since receiving him he has ate lettuce which he loves I got him eating calcium on Saturday mixed with the lettuce
A37: 1(3a) | B37: 1 | C37: 1 | F37: =_xlfn.XLOOKUP($A:$A,'Index New'!C:C,'Index New'!E:E,"") -> To take in through the mouth as food. To ingest, chew, and swallow in turn. | G37: =_xlfn.LET( _xlpm.r, _xlfn.XLOOKUP(A37,'Index New'!C:C,'Index New'!F:F,""), IF(_xlpm.r=0,"",_xlpm.r) ) | H37: eat | I37: ppt | J37: ate | K37: 76 | L37: tortoiseforum.org | M37: he loves I got him eating calcium on Saturday mixed with the lettuce he has ate blue berries and tomatoes and also cabbage at one point. Yesterday and the day
A38: 1(3a) | B38: 1 | C38: 1 | F38: =_xlfn.XLOOKUP($A:$A,'Index New'!C:C,'Index New'!E:E,"") -> To take in through the mouth as food. To ingest, chew, and swallow in turn. | G38: =_xlfn.LET( _xlpm.r, _xlfn.XLOOKUP(A38,'Index New'!C:C,'Index New'!F:F,""), IF(_xlpm.r=0,"",_xlpm.r) ) | H38: eat | I38: ppt | J38: ate | K38: 81 | L38: everydaymaven.com | M38: lasagna would be the first ever recipe I want to try. We've never ate or tasted lasagna simply because of the quantity of cheese. Kiran
A39: 1(3a) | B39: 1 | C39: 1 | F39: =_xlfn.XLOOKUP($A:$A,'Index New'!C:C,'Index New'!E:E,"") -> To take in through the mouth as food. To ingest, chew, and swallow in turn. | G39: =_xlfn.LET( _xlpm.r, _xlfn.XLOOKUP(A39,'Index New'!C:C,'Index New'!F:F,""), IF(_xlpm.r=0,"",_xlpm.r) ) | H39: eat | I39: ppt | J39: ate | K39: 83 | L39: babyprediction.net | M39: the bigger dog might have been a carrier of a disease or she could have ate something she shouldn't so I advise you to call the vet and ask.
A40: 1(4a) | B40: 1 | C40: 1 | D40: 1 | F40: =_xlfn.XLOOKUP($A:$A,'Index New'!C:C,'Index New'!E:E,"") -> To destroy, consume, or waste by or as if by eating. "Expenses ate up the profits." "gadgets that eat up too much space" | G40: =_xlfn.LET( _xlpm.r, _xlfn.XLOOKUP(A40,'Index New'!C:C,'Index New'!F:F,""), IF(_xlpm.r=0,"",_xlpm.r) ) | H40: eat | I40: ppt | J40: ate | K40: 87 | L40: reason.com (1) | M40: would have come in there thinking he was King/CEO and the bureaucracy would have ate him alive. # Does anyone here think the dynasty issue will hurt Hillary in
A41: 1(8a) | B41: 1 | D41: 1 | E41: 1 | F41: =_xlfn.XLOOKUP($A:$A,'Index New'!C:C,'Index New'!E:E,"") -> Phrases: eat it (to fall or be injured) | G41: =_xlfn.LET( _xlpm.r, _xlfn.XLOOKUP(A41,'Index New'!C:C,'Index New'!F:F,""), IF(_xlpm.r=0,"",_xlpm.r) ) -> I added this one. | H41: eat | I41: ppt | J41: ate | K41: 88 | L41: drtomprichard.com | M41: I, there was always respect and admiration from my end. You might have ate my ass out or been short and to the point at times but I realized
A42: 1(3a) | B42: 1 | C42: 1 | F42: =_xlfn.XLOOKUP($A:$A,'Index New'!C:C,'Index New'!E:E,"") -> To take in through the mouth as food. To ingest, chew, and swallow in turn. | G42: =_xlfn.LET( _xlpm.r, _xlfn.XLOOKUP(A42,'Index New'!C:C,'Index New'!F:F,""), IF(_xlpm.r=0,"",_xlpm.r) ) | H42: eat | I42: ppt | J42: ate | K42: 91 | L42: thebloggess.com | M42: Wheaton? I've come to one conclusion.... PAINT CHIPS... he must have ate a lot of them as a child. Margarita recently posted.. Hunger Games Movie
A43: 1(1a) | F43: =_xlfn.XLOOKUP($A:$A,'Index New'!C:C,'Index New'!E:E,"") -> To take food or a meal. | G43: =_xlfn.LET( _xlpm.r, _xlfn.XLOOKUP(A43,'Index New'!C:C,'Index New'!F:F,""), IF(_xlpm.r=0,"",_xlpm.r) ) | H43: eat | I43: ppt | J43: ate | K43: 92 | L43: Jersey Shore | M43: . - PARM? - YO, I'M STARVING TOO. I HAVE N'T ATE ALL DAY. - WELL, I GUESS YOU'RE GON NA BE HAPPY,
A44: 1(3a) | B44: 1 | C44: 1 | F44: =_xlfn.XLOOKUP($A:$A,'Index New'!C:C,'Index New'!E:E,"") -> To take in through the mouth as food. To ingest, chew, and swallow in turn. | G44: =_xlfn.LET( _xlpm.r, _xlfn.XLOOKUP(A44,'Index New'!C:C,'Index New'!F:F,""), IF(_xlpm.r=0,"",_xlpm.r) ) | H44: eat | I44: ppt | J44: ate | K44: 93 | L44: Cougar Town | M44: Until he tried to share a hot dog with one, And it ain't ate the whole t. Very selfish. Oh, that's right. His new
A45: 1(3a) | B45: 1 | C45: 1 | F45: =_xlfn.XLOOKUP($A:$A,'Index New'!C:C,'Index New'!E:E,"") -> To take in through the mouth as food. To ingest, chew, and swallow in turn. | G45: =_xlfn.LET( _xlpm.r, _xlfn.XLOOKUP(A45,'Index New'!C:C,'Index New'!F:F,""), IF(_xlpm.r=0,"",_xlpm.r) ) | H45: eat | I45: ppt | J45: ate | K45: 94 | L45: Boardwalk Empire | M45: so he could be identified. - He was identified. The fish could have ate his face off, Eli. He could have drifted to nova Scotia. Use
A46: 1(3a) | B46: 1 | C46: 1 | F46: =_xlfn.XLOOKUP($A:$A,'Index New'!C:C,'Index New'!E:E,"") -> To take in through the mouth as food. To ingest, chew, and swallow in turn. | G46: =_xlfn.LET( _xlpm.r, _xlfn.XLOOKUP(A46,'Index New'!C:C,'Index New'!F:F,""), IF(_xlpm.r=0,"",_xlpm.r) ) | H46: eat | I46: ppt | J46: ate | K46: 97 | L46: Everybody Hates Chris | M46: lucky. They're coming, quick, hide behind these greens. Should've ate some greens before I came and asked you. Ooh, you better watch your
A47: 1(3a) | B47: 1 | C47: 1 | F47: =_xlfn.XLOOKUP($A:$A,'Index New'!C:C,'Index New'!E:E,"") -> To take in through the mouth as food. To ingest, chew, and swallow in turn. | G47: =_xlfn.LET( _xlpm.r, _xlfn.XLOOKUP(A47,'Index New'!C:C,'Index New'!F:F,""), IF(_xlpm.r=0,"",_xlpm.r) ) | H47: eat | I47: ppt | J47: ate | K47: 98 | L47: NCIS | M47: dog meat? Looks like the same crap we had yesterday. You should've ate it all yesterday. Anyone seen Lieutenant Ferris? Check the head, sir.
A48: 1(3a) | B48: 1 | C48: 1 | F48: =_xlfn.XLOOKUP($A:$A,'Index New'!C:C,'Index New'!E:E,"") -> To take in through the mouth as food. To ingest, chew, and swallow in turn. | G48: =_xlfn.LET( _xlpm.r, _xlfn.XLOOKUP(A48,'Index New'!C:C,'Index New'!F:F,""), IF(_xlpm.r=0,"",_xlpm.r) ) | H48: eat | I48: ppt | J48: ate | K48: 99 | L48: Everybody Hates Chris | M48: . Mmm. This is good! If we had ladders, he'd have ate the asbestos. I want one! Me, too! Me, too!
A49: 1(1a) | F49: =_xlfn.XLOOKUP($A:$A,'Index New'!C:C,'Index New'!E:E,"") -> To take food or a meal. | G49: =_xlfn.LET( _xlpm.r, _xlfn.XLOOKUP(A49,'Index New'!C:C,'Index New'!F:F,""), IF(_xlpm.r=0,"",_xlpm.r) ) | H49: eat | I49: ppt | J49: ate | K49: 100 | L49: Deadwood | M49: for tonight, whoever you might want to tell I'll drink after I've ate Nuh-uh, no no You don't want you don't want to go in
A50: 1(1a) | F50: =_xlfn.XLOOKUP($A:$A,'Index New'!C:C,'Index New'!E:E,"") -> To take food or a meal. | G50: =_xlfn.LET( _xlpm.r, _xlfn.XLOOKUP(A50,'Index New'!C:C,'Index New'!F:F,""), IF(_xlpm.r=0,"",_xlpm.r) ) | H50: eat | I50: ppt | J50: ate | K50: 108 | L50: Ford v Ferrari | M50: ) Mandem a-call me Bruce Lee (m) (m) I ain't ate properly for two weeks (m) (m) Probably should try and get
A51: 1(3a) | B51: 1 | C51: 1 | F51: =_xlfn.XLOOKUP($A:$A,'Index New'!C:C,'Index New'!E:E,"") -> To take in through the mouth as food. To ingest, chew, and swallow in turn. | G51: =_xlfn.LET( _xlpm.r, _xlfn.XLOOKUP(A51,'Index New'!C:C,'Index New'!F:F,""), IF(_xlpm.r=0,"",_xlpm.r) ) | H51: eat | I51: ppt | J51: ate | K51: 109 | L51: Ambition | M51: hooking up now or what? So I'VE drank all of your wine and ate all of this delicious food. It's only right I, myself, add
A52: 1(3a) | B52: 1 | C52: 1 | F52: =_xlfn.XLOOKUP($A:$A,'Index New'!C:C,'Index New'!E:E,"") -> To take in through the mouth as food. To ingest, chew, and swallow in turn. | G52: =_xlfn.LET( _xlpm.r, _xlfn.XLOOKUP(A52,'Index New'!C:C,'Index New'!F:F,""), IF(_xlpm.r=0,"",_xlpm.r) ) | H52: eat | I52: ppt | J52: ate | K52: 110 | L52: HeartBreak | M52: George, I think about it all the time. I think I should have ate the scorpion. I should have ate it. Listen, I want you to
A53: 1(3a) | B53: 1 | C53: 1 | F53: =_xlfn.XLOOKUP($A:$A,'Index New'!C:C,'Index New'!E:E,"") -> To take in through the mouth as food. To ingest, chew, and swallow in turn. | G53: =_xlfn.LET( _xlpm.r, _xlfn.XLOOKUP(A53,'Index New'!C:C,'Index New'!F:F,""), IF(_xlpm.r=0,"",_xlpm.r) ) | H53: eat | I53: ppt | J53: ate | K53: 111 | L53: HeartBreak | M53: the time. I think I should have ate the scorpion. I should have ate it. Listen, I want you to do me a favor. Do you
A54: 1(1a) | F54: =_xlfn.XLOOKUP($A:$A,'Index New'!C:C,'Index New'!E:E,"") -> To take food or a meal. | G54: =_xlfn.LET( _xlpm.r, _xlfn.XLOOKUP(A54,'Index New'!C:C,'Index New'!F:F,""), IF(_xlpm.r=0,"",_xlpm.r) ) | H54: eat | I54: ppt | J54: ate | K54: 115 | L54: Slapped! The Movie | M54: , indeed (m) (m) I go in like I ain't ate in weeks (m) (m) You're never the sameI'm choppin
A55: 1(1a) | F55: =_xlfn.XLOOKUP($A:$A,'Index New'!C:C,'Index New'!E:E,"") -> To take food or a meal. | G55: =_xlfn.LET( _xlpm.r, _xlfn.XLOOKUP(A55,'Index New'!C:C,'Index New'!F:F,""), IF(_xlpm.r=0,"",_xlpm.r) ) | H55: eat | I55: ppt | J55: ate | K55: 116 | L55: Bk:WorldMadeStraight | M55: he was about to leave his father stopped him. " We haven't ate yet. " " I'll get something in town, " Travis replied
A56: 1(3a) | B56: 1 | C56: 1 | F56: =_xlfn.XLOOKUP($A:$A,'Index New'!C:C,'Index New'!E:E,"") -> To take in through the mouth as food. To ingest, chew, and swallow in turn. | G56: =_xlfn.LET( _xlpm.r, _xlfn.XLOOKUP(A56,'Index New'!C:C,'Index New'!F:F,""), IF(_xlpm.r=0,"",_xlpm.r) ) | H56: eat | I56: ppt | J56: ate | K56: 118 | L56: Diary of a Wimpy Kid: The Long Haul | M56: let yourself go # # Let yourself go # I knew I shouldn't have ate that 9th stick of butter. Ninth? BEARDO: You! Stop the ride
A57: 1(1a) | F57: =_xlfn.XLOOKUP($A:$A,'Index New'!C:C,'Index New'!E:E,"") -> To take food or a meal. | G57: =_xlfn.LET( _xlpm.r, _xlfn.XLOOKUP(A57,'Index New'!C:C,'Index New'!F:F,""), IF(_xlpm.r=0,"",_xlpm.r) ) | H57: eat | I57: ppt | J57: ate | K57: 119 | L57: Cut to the Chase | M57: - We ain't been home. We ain't slept, we ain't ate. Wait a damn minute. - Will you get the hell outta the way
A58: 1(3a) | B58: 1 | C58: 1 | F58: =_xlfn.XLOOKUP($A:$A,'Index New'!C:C,'Index New'!E:E,"") -> To take in through the mouth as food. To ingest, chew, and swallow in turn. | G58: =_xlfn.LET( _xlpm.r, _xlfn.XLOOKUP(A58,'Index New'!C:C,'Index New'!F:F,""), IF(_xlpm.r=0,"",_xlpm.r) ) | H58: eat | I58: ppt | J58: ate | K58: 121 | L58: FantasySciFi | M58: , but her eyes still looked hollowed out. She asked me if I had ate my dinner. I lied, then asked her how she was feeling. #
A59: 1(4a) | B59: 1 | C59: 1 | D59: 1 | E59: 1 | F59: =_xlfn.XLOOKUP($A:$A,'Index New'!C:C,'Index New'!E:E,"") -> To destroy, consume, or waste by or as if by eating. "Expenses ate up the profits." "gadgets that eat up too much space" | G59: =_xlfn.LET( _xlpm.r, _xlfn.XLOOKUP(A59,'Index New'!C:C,'Index New'!F:F,""), IF(_xlpm.r=0,"",_xlpm.r) ) | H59: eat | I59: ppt | J59: ate | K59: 123 | L59: RollingStone.com | M59: It was a situation where any music that I released, it would've been ate by Def Jam. So now I'm wide open. We fittin' getting
A60: 1(1a) | F60: =_xlfn.XLOOKUP($A:$A,'Index New'!C:C,'Index New'!E:E,"") -> To take food or a meal. | G60: =_xlfn.LET( _xlpm.r, _xlfn.XLOOKUP(A60,'Index New'!C:C,'Index New'!F:F,""), IF(_xlpm.r=0,"",_xlpm.r) ) | H60: eat | I60: ppt | J60: ate | K60: 128 | L60: CBS: 48 Hours | M60: RICK-JANCHA- (in-co# Did you ask her how long it had been before she'd ate? MATTHEW-DEPANICIS-# No. RICK-JANCHA- (in-co# Did you ask her when the last time she
A61: 1(4a) | B61: 1 | C61: 1 | D61: 1 | F61: =_xlfn.XLOOKUP($A:$A,'Index New'!C:C,'Index New'!E:E,"") -> To destroy, consume, or waste by or as if by eating. "Expenses ate up the profits." "gadgets that eat up too much space" | G61: =_xlfn.LET( _xlpm.r, _xlfn.XLOOKUP(A61,'Index New'!C:C,'Index New'!F:F,""), IF(_xlpm.r=0,"",_xlpm.r) ) | H61: eat | I61: ppt | J61: ate | K61: 129 | L61: Bk:Captive | M61: long ago not to bother much with my appearancebut the other responsibilities I had always ate up a good chunk of time. I threw back the covers and forced myself
A62: 1(3a) | B62: 1 | C62: 1 | D62: ? | F62: =_xlfn.XLOOKUP($A:$A,'Index New'!C:C,'Index New'!E:E,"") -> To take in through the mouth as food. To ingest, chew, and swallow in turn. | G62: =_xlfn.LET( _xlpm.r, _xlfn.XLOOKUP(A62,'Index New'!C:C,'Index New'!F:F,""), IF(_xlpm.r=0,"",_xlpm.r) ) | H62: eat | I62: ppt | J62: ate | K62: 134 | L62: ... Mates vs. The Zombie Apocalypse | M62: to time it with the rover. We go out too early, we get ate. We go out too late... - We'll be eaten. - Exactly
A63: 1(3a) | B63: 1 | C63: 1 | F63: =_xlfn.XLOOKUP($A:$A,'Index New'!C:C,'Index New'!E:E,"") -> To take in through the mouth as food. To ingest, chew, and swallow in turn. | G63: =_xlfn.LET( _xlpm.r, _xlfn.XLOOKUP(A63,'Index New'!C:C,'Index New'!F:F,""), IF(_xlpm.r=0,"",_xlpm.r) ) | H63: eat | I63: ppt | J63: ate | K63: 138 | L63: Ploughshares | M63: no dog, " Lyle said. " Not no more. Must of got ate up by pigs. " He said this as though he himself believed it,
A64: 1(3a) | B64: 1 | C64: 1 | F64: =_xlfn.XLOOKUP($A:$A,'Index New'!C:C,'Index New'!E:E,"") -> To take in through the mouth as food. To ingest, chew, and swallow in turn. | G64: =_xlfn.LET( _xlpm.r, _xlfn.XLOOKUP(A64,'Index New'!C:C,'Index New'!F:F,""), IF(_xlpm.r=0,"",_xlpm.r) ) | H64: eat | I64: ppt | J64: ate | K64: 141 | L64: Sand Castles | M64: matter how small it is. Your heart shall be torn out and roasted and ate! I'll get them for ya, sir. Let God strike ya dead
A65: 1(3a) | B65: 1 | C65: 1 | F65: =_xlfn.XLOOKUP($A:$A,'Index New'!C:C,'Index New'!E:E,"") -> To take in through the mouth as food. To ingest, chew, and swallow in turn. | G65: =_xlfn.LET( _xlpm.r, _xlfn.XLOOKUP(A65,'Index New'!C:C,'Index New'!F:F,""), IF(_xlpm.r=0,"",_xlpm.r) ) | H65: eat | I65: ppt | J65: ate | K65: 144 | L65: Bk:TrailWest | M65: sternly. " I know how you dogs are. Even if you'd just ate a whole steer, you'd still be beggin' for cake. " The
A66: 1(3a) | B66: 1 | C66: 1 | F66: =_xlfn.XLOOKUP($A:$A,'Index New'!C:C,'Index New'!E:E,"") -> To take in through the mouth as food. To ingest, chew, and swallow in turn. | G66: =_xlfn.LET( _xlpm.r, _xlfn.XLOOKUP(A66,'Index New'!C:C,'Index New'!F:F,""), IF(_xlpm.r=0,"",_xlpm.r) ) | H66: eat | I66: ppt | J66: ate | K66: 150 | L66: Line of Duty | M66: n't about to go to jail. Well, you should have sat there and ate your fucking torta, asshole. - Let's get the fuck out of here
A67: 1(3a) | B67: 1 | C67: 1 | F67: =_xlfn.XLOOKUP($A:$A,'Index New'!C:C,'Index New'!E:E,"") -> To take in through the mouth as food. To ingest, chew, and swallow in turn. | G67: =_xlfn.LET( _xlpm.r, _xlfn.XLOOKUP(A67,'Index New'!C:C,'Index New'!F:F,""), IF(_xlpm.r=0,"",_xlpm.r) ) | H67: eat | I67: ppt | J67: ate | K67: 151 | L67: 12 O'Clock Boys | M67: 9:00 this morning, and it's 6:00 this evening. So he haven't ate nothin' or nothin'. This don't make sense because he didn't
A68: 1(4a) | B68: 1 | C68: 1 | D68: 1 | F68: =_xlfn.XLOOKUP($A:$A,'Index New'!C:C,'Index New'!E:E,"") -> To destroy, consume, or waste by or as if by eating. "Expenses ate up the profits." "gadgets that eat up too much space" | G68: =_xlfn.LET( _xlpm.r, _xlfn.XLOOKUP(A68,'Index New'!C:C,'Index New'!F:F,""), IF(_xlpm.r=0,"",_xlpm.r) ) | H68: eat | I68: ppt | J68: ate | K68: 156 | L68: LUV | M68: 's going down... on my streets? - Nigga, those streets would've ate your old ass up if i wasn't out there for you. Them streets
A69: 1(4a) | B69: 1 | C69: 1 | F69: =_xlfn.XLOOKUP($A:$A,'Index New'!C:C,'Index New'!E:E,"") -> To destroy, consume, or waste by or as if by eating. "Expenses ate up the profits." "gadgets that eat up too much space" | G69: =_xlfn.LET( _xlpm.r, _xlfn.XLOOKUP(A69,'Index New'!C:C,'Index New'!F:F,""), IF(_xlpm.r=0,"",_xlpm.r) ) | H69: eat | I69: ppt | J69: ate | K69: 157 | L69: Black Rock | M69: what we killed, and, uh, well, so far we ain't ate a thing. Oh. Sucks. - Yeah. - All right. I
A70: 1(8a) | B70: 1 | D70: 1 | E70: 1 | F70: =_xlfn.XLOOKUP($A:$A,'Index New'!C:C,'Index New'!E:E,"") -> Phrases: eat it (to fall or be injured) | G70: =_xlfn.LET( _xlpm.r, _xlfn.XLOOKUP(A70,'Index New'!C:C,'Index New'!F:F,""), IF(_xlpm.r=0,"",_xlpm.r) ) -> I added this one. | H70: eat | I70: ppt | J70: ate | K70: 158 | L70: CNN_Morgan | M70: between the husband and wife, some really great things happen. If you get ate little off because the husband -- the Bible says the man has to love the
A71: 1(3a) | B71: 1 | C71: 1 | F71: =_xlfn.XLOOKUP($A:$A,'Index New'!C:C,'Index New'!E:E,"") -> To take in through the mouth as food. To ingest, chew, and swallow in turn. | G71: =_xlfn.LET( _xlpm.r, _xlfn.XLOOKUP(A71,'Index New'!C:C,'Index New'!F:F,""), IF(_xlpm.r=0,"",_xlpm.r) ) | H71: eat | I71: ppt | J71: ate | K71: 162 | L71: I Can Do Bad All by Myself | M71: Them children. Clap your hands, girls! Y'all eating like y'all ain't ate nothing in days. I don't know why the hell you feeding these children
A72: 1(4a) | B72: 1 | C72: 1 | D72: 1 | F72: =_xlfn.XLOOKUP($A:$A,'Index New'!C:C,'Index New'!E:E,"") -> To destroy, consume, or waste by or as if by eating. "Expenses ate up the profits." "gadgets that eat up too much space" | G72: =_xlfn.LET( _xlpm.r, _xlfn.XLOOKUP(A72,'Index New'!C:C,'Index New'!F:F,""), IF(_xlpm.r=0,"",_xlpm.r) ) | H72: eat | I72: ppt | J72: ate | K72: 163 | L72: ...onderful Whites of West Virginia | M72: tell high-test from regular, just by the scent. You know, it'd ate a hole out my brain. And the doctor told my wife when they come
A73: 1(1a) | F73: =_xlfn.XLOOKUP($A:$A,'Index New'!C:C,'Index New'!E:E,"") -> To take food or a meal. | G73: =_xlfn.LET( _xlpm.r, _xlfn.XLOOKUP(A73,'Index New'!C:C,'Index New'!F:F,""), IF(_xlpm.r=0,"",_xlpm.r) ) | H73: eat | I73: ppt | J73: ate | K73: 164 | L73: Where God Left His Shoes | M73: door. Oh, man. I'm hungry. Well, you should have ate at the shelter. Can we eat when we get off the train? No
A74: 1(4a) | B74: 1 | C74: 1 | D74: 1 | E74: 1 | F74: =_xlfn.XLOOKUP($A:$A,'Index New'!C:C,'Index New'!E:E,"") -> To destroy, consume, or waste by or as if by eating. "Expenses ate up the profits." "gadgets that eat up too much space" | G74: =_xlfn.LET( _xlpm.r, _xlfn.XLOOKUP(A74,'Index New'!C:C,'Index New'!F:F,""), IF(_xlpm.r=0,"",_xlpm.r) ) | H74: eat | I74: ppt | J74: ate | K74: 165 | L74: ...Chainsaw Massacre: The Beginning | M74: who eats? Or are you gon na be the poor sorry motherfucker who gets ate? # If that mockingbird don't sing... # # Mama's gon na
A75: 1(3a) | B75: 1 | C75: 1 | F75: =_xlfn.XLOOKUP($A:$A,'Index New'!C:C,'Index New'!E:E,"") -> To take in through the mouth as food. To ingest, chew, and swallow in turn. | G75: =_xlfn.LET( _xlpm.r, _xlfn.XLOOKUP(A75,'Index New'!C:C,'Index New'!F:F,""), IF(_xlpm.r=0,"",_xlpm.r) ) | H75: eat | I75: ppt | J75: ate | K75: 166 | L75: Missing in America | M75: eat. When your dad comes back and you're dead because you ain't ate nothin' it ain't my fault. I can't cook. Henry says
A76: 1(1a) | F76: =_xlfn.XLOOKUP($A:$A,'Index New'!C:C,'Index New'!E:E,"") -> To take food or a meal. | G76: =_xlfn.LET( _xlpm.r, _xlfn.XLOOKUP(A76,'Index New'!C:C,'Index New'!F:F,""), IF(_xlpm.r=0,"",_xlpm.r) ) | H76: eat | I76: ppt | J76: ate | K76: 167 | L76: Everybody Hates Chris | M76: have shot my father in the ass and still got the room. Have you ate yet? There you go. Come on up here, huh? Watch out
A77: 1(3a) | B77: 1 | C77: 1 | F77: =_xlfn.XLOOKUP($A:$A,'Index New'!C:C,'Index New'!E:E,"") -> To take in through the mouth as food. To ingest, chew, and swallow in turn. | G77: =_xlfn.LET( _xlpm.r, _xlfn.XLOOKUP(A77,'Index New'!C:C,'Index New'!F:F,""), IF(_xlpm.r=0,"",_xlpm.r) ) | H77: eat | I77: ppt | J77: ate | K77: 171 | L77: Zombiegeddon | M77: the world. He's a heavy son of a bitch. He must've ate twice as much groceries as before we had. Come on, man. This
A78: 1(4a) | B78: 1 | C78: 1 | D78: 1 | F78: =_xlfn.XLOOKUP($A:$A,'Index New'!C:C,'Index New'!E:E,"") -> To destroy, consume, or waste by or as if by eating. "Expenses ate up the profits." "gadgets that eat up too much space" | G78: =_xlfn.LET( _xlpm.r, _xlfn.XLOOKUP(A78,'Index New'!C:C,'Index New'!F:F,""), IF(_xlpm.r=0,"",_xlpm.r) ) | H78: eat | I78: ppt | J78: ate | K78: 173 | L78: Firefly | M78: the atmo before the explosion shut it all down. Most of that oxygen got ate up by the fire on its way out the door. Well, whatever's
A79: 1(3a) | B79: 1 | C79: 1 | F79: =_xlfn.XLOOKUP($A:$A,'Index New'!C:C,'Index New'!E:E,"") -> To take in through the mouth as food. To ingest, chew, and swallow in turn. | G79: =_xlfn.LET( _xlpm.r, _xlfn.XLOOKUP(A79,'Index New'!C:C,'Index New'!F:F,""), IF(_xlpm.r=0,"",_xlpm.r) ) | H79: eat | I79: ppt | J79: ate | K79: 177 | L79: Ride with the Devil | M79: before they hung him. He said the dirt was so rich you could've ate it like porridge. They have very good dirt up there. Short grow season
A80: 1(3a) | B80: 1 | C80: 1 | F80: =_xlfn.XLOOKUP($A:$A,'Index New'!C:C,'Index New'!E:E,"") -> To take in through the mouth as food. To ingest, chew, and swallow in turn. | G80: =_xlfn.LET( _xlpm.r, _xlfn.XLOOKUP(A80,'Index New'!C:C,'Index New'!F:F,""), IF(_xlpm.r=0,"",_xlpm.r) ) | H80: eat | I80: ppt | J80: ate | K80: 181 | L80: Dr. Katz, Profession... | M80: work day. - Are you going? - Probably. I shouldn't have ate a pre-dinner. Y'know, your interpretation of hors d'oeuvres is so broad. Umm
A81: 1(3a) | B81: 1 | C81: 1 | F81: =_xlfn.XLOOKUP($A:$A,'Index New'!C:C,'Index New'!E:E,"") -> To take in through the mouth as food. To ingest, chew, and swallow in turn. | G81: =_xlfn.LET( _xlpm.r, _xlfn.XLOOKUP(A81,'Index New'!C:C,'Index New'!F:F,""), IF(_xlpm.r=0,"",_xlpm.r) ) | H81: eat | I81: ppt | J81: ate | K81: 182 | L81: The Object of My Affection | M81: - Oh, God. Open the windows. Daddy, you never should have ate that herring. Fan me with something. Is that The New Yorker? Fan
A82: 1(1a) | F82: =_xlfn.XLOOKUP($A:$A,'Index New'!C:C,'Index New'!E:E,"") -> To take food or a meal. | G82: =_xlfn.LET( _xlpm.r, _xlfn.XLOOKUP(A82,'Index New'!C:C,'Index New'!F:F,""), IF(_xlpm.r=0,"",_xlpm.r) ) | H82: eat | I82: ppt | J82: ate | K82: 190 | L82: NYPD Blue | M82: wan na start. slide that soup my way, huh? i haven't ate all day either. sure. [sniffing] mmm. how's work? you got
A83: 1(3a) | B83: 1 | C83: 1 | F83: =_xlfn.XLOOKUP($A:$A,'Index New'!C:C,'Index New'!E:E,"") -> To take in through the mouth as food. To ingest, chew, and swallow in turn. | G83: =_xlfn.LET( _xlpm.r, _xlfn.XLOOKUP(A83,'Index New'!C:C,'Index New'!F:F,""), IF(_xlpm.r=0,"",_xlpm.r) ) | H83: eat | I83: ppt | J83: ate | K83: 192 | L83: Jefferson in Paris | M83: it. They don't even know how to eat it like it should be ate. Why, how do you eat it? You roasts it, then you
A84: 1(3a) | B84: 1 | C84: 1 | F84: =_xlfn.XLOOKUP($A:$A,'Index New'!C:C,'Index New'!E:E,"") -> To take in through the mouth as food. To ingest, chew, and swallow in turn. | G84: =_xlfn.LET( _xlpm.r, _xlfn.XLOOKUP(A84,'Index New'!C:C,'Index New'!F:F,""), IF(_xlpm.r=0,"",_xlpm.r) ) | H84: eat | I84: ppt | J84: ate | K84: 193 | L84: Kiss of Death | M84: is he, a matador? Besides, the last I heard that tape got ate by the garbage monster. Jimmy? You got a phone call. - Hello
A85: 1(3a) | B85: 1 | C85: 1 | F85: =_xlfn.XLOOKUP($A:$A,'Index New'!C:C,'Index New'!E:E,"") -> To take in through the mouth as food. To ingest, chew, and swallow in turn. | G85: =_xlfn.LET( _xlpm.r, _xlfn.XLOOKUP(A85,'Index New'!C:C,'Index New'!F:F,""), IF(_xlpm.r=0,"",_xlpm.r) ) | H85: eat | I85: ppt | J85: ate | K85: 194 | L85: Space: Above and Beyond | M85: ! [Engine_Stops] [Alarm_Continues] I'm outta fuel. Well, I guess Ray [Butts] has ate his last pancake. It has been a honor, 58. Good-bye, sir
A86: 1(4a) | B86: 1 | C86: 1 | D86: 1 | F86: =_xlfn.XLOOKUP($A:$A,'Index New'!C:C,'Index New'!E:E,"") -> To destroy, consume, or waste by or as if by eating. "Expenses ate up the profits." "gadgets that eat up too much space" | G86: =_xlfn.LET( _xlpm.r, _xlfn.XLOOKUP(A86,'Index New'!C:C,'Index New'!F:F,""), IF(_xlpm.r=0,"",_xlpm.r) ) | H86: eat | I86: ppt | J86: ate | K86: 196 | L86: Airheads | M86: the radio earlier. You heard it for about five seconds and then it got ate. Well, Chazz, my man, it's not just the music,
A87: 1(3a) | B87: 1 | C87: 1 | F87: =_xlfn.XLOOKUP($A:$A,'Index New'!C:C,'Index New'!E:E,"") -> To take in through the mouth as food. To ingest, chew, and swallow in turn. | G87: =_xlfn.LET( _xlpm.r, _xlfn.XLOOKUP(A87,'Index New'!C:C,'Index New'!F:F,""), IF(_xlpm.r=0,"",_xlpm.r) ) | H87: eat | I87: ppt | J87: ate | K87: 197 | L87: Crooklyn | M87: . - I'm hungry. Too bad, kitchen's closed. Should have ate more than three peas. - " I ate three peas! " - Shut
A88: 1(3a) | B88: 1 | C88: 1 | F88: =_xlfn.XLOOKUP($A:$A,'Index New'!C:C,'Index New'!E:E,"") -> To take in through the mouth as food. To ingest, chew, and swallow in turn. | G88: =_xlfn.LET( _xlpm.r, _xlfn.XLOOKUP(A88,'Index New'!C:C,'Index New'!F:F,""), IF(_xlpm.r=0,"",_xlpm.r) ) | H88: eat | I88: ppt | J88: ate | K88: 198 | L88: Northern Exposure | M88: all? Brother, I don't remember anything at all. I must have ate a lot of peyote out in the desert' cause my head's like a
A89: 1(1a) | F89: =_xlfn.XLOOKUP($A:$A,'Index New'!C:C,'Index New'!E:E,"") -> To take food or a meal. | G89: =_xlfn.LET( _xlpm.r, _xlfn.XLOOKUP(A89,'Index New'!C:C,'Index New'!F:F,""), IF(_xlpm.r=0,"",_xlpm.r) ) | H89: eat | I89: ppt | J89: ate | K89: 199 | L89: Queen | M89: folk. WOMAN: please, master. I so hungry. I ain't ate in days. - Haven't seen you here before. - No, ma'am
A90: 1(1a) | F90: =_xlfn.XLOOKUP($A:$A,'Index New'!C:C,'Index New'!E:E,"") -> To take food or a meal. | G90: =_xlfn.LET( _xlpm.r, _xlfn.XLOOKUP(A90,'Index New'!C:C,'Index New'!F:F,""), IF(_xlpm.r=0,"",_xlpm.r) ) | H90: eat | I90: ppt | J90: ate | K90: 200 | L90: Queen | M90: of eating. MAN: well, hush up, man. I ain't ate yet. [ALEC_LAUGHS] ALEC: I just saying can't find a good hog up
A91: 1(3a) | B91: 1 | C91: 1 | F91: =_xlfn.XLOOKUP($A:$A,'Index New'!C:C,'Index New'!E:E,"") -> To take in through the mouth as food. To ingest, chew, and swallow in turn. | G91: =_xlfn.LET( _xlpm.r, _xlfn.XLOOKUP(A91,'Index New'!C:C,'Index New'!F:F,""), IF(_xlpm.r=0,"",_xlpm.r) ) | H91: eat | I91: ppt | J91: ate | K91: 206 | L91: FantasySciFi | M91: the process moderately sick-making? " " Not after all the raw ersters I've ate. I guess Bluddy's clothes and shoes are inside out, too? "
A92: 1(3a) | B92: 1 | C92: 1 | F92: =_xlfn.XLOOKUP($A:$A,'Index New'!C:C,'Index New'!E:E,"") -> To take in through the mouth as food. To ingest, chew, and swallow in turn. | G92: =_xlfn.LET( _xlpm.r, _xlfn.XLOOKUP(A92,'Index New'!C:C,'Index New'!F:F,""), IF(_xlpm.r=0,"",_xlpm.r) ) | H92: eat | I92: ppt | J92: ate | K92: 207 | L92: ArkansasRev | M92: and biscuit or french toast with syrup. My stomach pit-empty cause I ain't ate nothing since yesterday lunch, and when I see kids go past with pig in
A93: 1(1a) | E93: 1 | F93: =_xlfn.XLOOKUP($A:$A,'Index New'!C:C,'Index New'!E:E,"") -> To take food or a meal. | G93: =_xlfn.LET( _xlpm.r, _xlfn.XLOOKUP(A93,'Index New'!C:C,'Index New'!F:F,""), IF(_xlpm.r=0,"",_xlpm.r) ) | H93: eat | I93: ppt | J93: ate | K93: 219 | L93: Callaloo | M93: time. We used to sit around after vittles was done and we all had ate our full, and we used to talk to each other. Tell each other
A94: 1(1a) | F94: =_xlfn.XLOOKUP($A:$A,'Index New'!C:C,'Index New'!E:E,"") -> To take food or a meal. | G94: =_xlfn.LET( _xlpm.r, _xlfn.XLOOKUP(A94,'Index New'!C:C,'Index New'!F:F,""), IF(_xlpm.r=0,"",_xlpm.r) ) | H94: eat | I94: ppt | J94: ate | K94: 232 | L94: NBC_Today | M94: Offscreen Voice: What did she say? Mr-GREG-LYNCH-1Da: Just that she hasn't ate in eight days and -- and she's hungry. FAW: And very anxious
A95: 1(3a) | B95: 1 | C95: 1 | F95: =_xlfn.XLOOKUP($A:$A,'Index New'!C:C,'Index New'!E:E,"") -> To take in through the mouth as food. To ingest, chew, and swallow in turn. | G95: =_xlfn.LET( _xlpm.r, _xlfn.XLOOKUP(A95,'Index New'!C:C,'Index New'!F:F,""), IF(_xlpm.r=0,"",_xlpm.r) ) | H95: eat | I95: ppt | J95: ate | K95: 238 | L95: SouthernRev | M95: We could at least get our strength back. The meat's got to be ate, and I bet you never ate squirrel before. You ought to try it
A96: 1(3a) | B96: 1 | C96: 1 | F96: =_xlfn.XLOOKUP($A:$A,'Index New'!C:C,'Index New'!E:E,"") -> To take in through the mouth as food. To ingest, chew, and swallow in turn. | G96: =_xlfn.LET( _xlpm.r, _xlfn.XLOOKUP(A96,'Index New'!C:C,'Index New'!F:F,""), IF(_xlpm.r=0,"",_xlpm.r) ) | H96: eat | I96: ppt | J96: ate | K96: 240 | L96: CBS_48Hours | M96: just dumped half of it down the sink, so she would think I had ate the whole thing. If I havent gained you know, Im a bad patient
A97: 1(3a) | B97: 1 | C97: 1 | E97: 1 | F97: =_xlfn.XLOOKUP($A:$A,'Index New'!C:C,'Index New'!E:E,"") -> To take in through the mouth as food. To ingest, chew, and swallow in turn. | G97: =_xlfn.LET( _xlpm.r, _xlfn.XLOOKUP(A97,'Index New'!C:C,'Index New'!F:F,""), IF(_xlpm.r=0,"",_xlpm.r) ) | H97: eat | I97: ppt | J97: ate | K97: 248 | L97: LitCavalcade | M97: pointing at the feet on the floor behind the blood bay. " He's ate Sheets. Ah, I knew he was a hard horse, but to eat
A98: 1(3a) | B98: 1 | C98: 1 | F98: =_xlfn.XLOOKUP($A:$A,'Index New'!C:C,'Index New'!E:E,"") -> To take in through the mouth as food. To ingest, chew, and swallow in turn. | G98: =_xlfn.LET( _xlpm.r, _xlfn.XLOOKUP(A98,'Index New'!C:C,'Index New'!F:F,""), IF(_xlpm.r=0,"",_xlpm.r) ) | H98: eat | I98: ppt | J98: ate | K98: 255 | L98: ParisRev | M98: miss me husband Donal. Ate be a shark. JOHNNY: 1871 he was ate be a shark. DOCTOR: Oh you should be trying to get over that
A99: 1(3a) | B99: 1 | C99: 1 | F99: =_xlfn.XLOOKUP($A:$A,'Index New'!C:C,'Index New'!E:E,"") -> To take in through the mouth as food. To ingest, chew, and swallow in turn. | G99: =_xlfn.LET( _xlpm.r, _xlfn.XLOOKUP(A99,'Index New'!C:C,'Index New'!F:F,""), IF(_xlpm.r=0,"",_xlpm.r) ) | H99: eat | I99: ppt | J99: ate | K99: 256 | L99: ParisRev | M99: Yalla-mallows and don't be starting on me. KATE: I thought you'd ate all the Yalla-mallows. EILEEN: I'd put a couple of Yalla-mallows aside for
A100: 1(3a) | B100: 1 | C100: 1 | F100: =_xlfn.XLOOKUP($A:$A,'Index New'!C:C,'Index New'!E:E,"") -> To take in through the mouth as food. To ingest, chew, and swallow in turn. | G100: =_xlfn.LET( _xlpm.r, _xlfn.XLOOKUP(A100,'Index New'!C:C,'Index New'!F:F,""), IF(_xlpm.r=0,"",_xlpm.r) ) | H100: eat | I100: ppt | J100: ate | K100: 265 | L100: ArkansasRev | M100: terrain, the distant Denali barely visible behind clouds. # " A guy got ate up in Tok this year, " said the one in the passenger seat.
...
